{
  "language": "Solidity",
  "sources": {
    "contracts/Test.sol": {
      "content": "// SPDX-License-Identifier: MIT\npragma solidity 0.8.11;\n\ncontract Test {\n    string public greeting;\n\n    constructor(string memory greeting_) {\n        greeting = greeting_;\n    }\n\n    function sayGreeting() public view returns (string memory) {\n        return greeting;\n    }\n}\n"
    }
  },
  "settings": {
    "optimizer": {
      "enabled": true,
      "runs": 200
    },
    "outputSelection": {
      "*": {
        "*": [
          "abi",
          "evm.bytecode",
          "evm.deployedBytecode",
          "evm.methodIdentifiers",
          "metadata",
          "devdoc",
          "userdoc",
          "storageLayout",
          "evm.gasEstimates"
        ],
        "": [
          "ast"
        ]
      }
    },
    "metadata": {
      "useLiteralContent": true
    }
  }
}